{
   "results" : [
      {
         "address_components" : [
            {
               "long_name" : "91",
               "short_name" : "91",
               "types" : [ "street_number" ]
            },
            {
               "long_name" : "Section 1, Chongren Road",
               "short_name" : "Section 1, Chongren Rd",
               "types" : [ "route" ]
            },
            {
               "long_name" : "²M¦¿¨½",
               "short_name" : "²M¦¿¨½",
               "types" : [ "administrative_area_level_4", "political" ]
            },
            {
               "long_name" : "Beitou District",
               "short_name" : "Beitou District",
               "types" : [ "administrative_area_level_3", "political" ]
            },
            {
               "long_name" : "Taipei City",
               "short_name" : "Taipei City",
               "types" : [ "administrative_area_level_1", "political" ]
            },
            {
               "long_name" : "Taiwan",
               "short_name" : "TW",
               "types" : [ "country", "political" ]
            },
            {
               "long_name" : "112",
               "short_name" : "112",
               "types" : [ "postal_code" ]
            }
         ],
         "formatted_address" : "No. 91, Section 1, Chongren Rd, Beitou District, Taipei City, Taiwan 112",
         "geometry" : {
            "bounds" : {
               "northeast" : {
                  "lat" : 25.1256573,
                  "lng" : 121.5016954
               },
               "southwest" : {
                  "lat" : 25.1256533,
                  "lng" : 121.5016772
               }
            },
            "location" : {
               "lat" : 25.1256533,
               "lng" : 121.5016772
            },
            "location_type" : "RANGE_INTERPOLATED",
            "viewport" : {
               "northeast" : {
                  "lat" : 25.12700428029151,
                  "lng" : 121.5030352802915
               },
               "southwest" : {
                  "lat" : 25.1243063197085,
                  "lng" : 121.5003373197085
               }
            }
         },
         "partial_match" : true,
         "place_id" : "Ei8xMTLlj7DngaPlj7DljJfluILljJfmipXljYDltIfku4Hot6_kuIDmrrU5MeiZnw",
         "types" : [ "street_address" ]
      }
   ],
   "status" : "OK"
}

