{
   "results" : [
      {
         "address_components" : [
            {
               "long_name" : "38",
               "short_name" : "38",
               "types" : [ "street_number" ]
            },
            {
               "long_name" : "Fuxing North Road",
               "short_name" : "Fuxing N Rd",
               "types" : [ "route" ]
            },
            {
               "long_name" : "力行里",
               "short_name" : "力行里",
               "types" : [ "administrative_area_level_4", "political" ]
            },
            {
               "long_name" : "Zhongshan District",
               "short_name" : "Zhongshan District",
               "types" : [ "administrative_area_level_3", "political" ]
            },
            {
               "long_name" : "Taipei City",
               "short_name" : "Taipei City",
               "types" : [ "administrative_area_level_1", "political" ]
            },
            {
               "long_name" : "Taiwan",
               "short_name" : "TW",
               "types" : [ "country", "political" ]
            },
            {
               "long_name" : "104",
               "short_name" : "104",
               "types" : [ "postal_code" ]
            }
         ],
         "formatted_address" : "No. 38, Fuxing N Rd, Zhongshan District, Taipei City, Taiwan 104",
         "geometry" : {
            "bounds" : {
               "northeast" : {
                  "lat" : 25.0491136,
                  "lng" : 121.5438496
               },
               "southwest" : {
                  "lat" : 25.049113,
                  "lng" : 121.5438308
               }
            },
            "location" : {
               "lat" : 25.0491136,
               "lng" : 121.5438308
            },
            "location_type" : "RANGE_INTERPOLATED",
            "viewport" : {
               "northeast" : {
                  "lat" : 25.0504622802915,
                  "lng" : 121.5451891802915
               },
               "southwest" : {
                  "lat" : 25.0477643197085,
                  "lng" : 121.5424912197085
               }
            }
         },
         "place_id" : "EiwxMDTlj7DngaPlj7DljJfluILkuK3lsbHljYDlvqnoiIjljJfot68zOOiZnw",
         "types" : [ "street_address" ]
      }
   ],
   "status" : "OK"
}

