{
   "results" : [
      {
         "address_components" : [
            {
               "long_name" : "34",
               "short_name" : "34",
               "types" : [ "street_number" ]
            },
            {
               "long_name" : "Lane 113, Section 3, Chongqing North Road",
               "short_name" : "Lane 113, Section 3, Chongqing N Rd",
               "types" : [ "route" ]
            },
            {
               "long_name" : "´­¶®¨½",
               "short_name" : "´­¶®¨½",
               "types" : [ "administrative_area_level_4", "political" ]
            },
            {
               "long_name" : "Datong District",
               "short_name" : "Datong District",
               "types" : [ "administrative_area_level_3", "political" ]
            },
            {
               "long_name" : "Taipei City",
               "short_name" : "Taipei City",
               "types" : [ "administrative_area_level_1", "political" ]
            },
            {
               "long_name" : "Taiwan",
               "short_name" : "TW",
               "types" : [ "country", "political" ]
            },
            {
               "long_name" : "103",
               "short_name" : "103",
               "types" : [ "postal_code" ]
            }
         ],
         "formatted_address" : "No. 34, Lane 113, Section 3, Chongqing N Rd, Datong District, Taipei City, Taiwan 103",
         "geometry" : {
            "location" : {
               "lat" : 25.0671914,
               "lng" : 121.515203
            },
            "location_type" : "ROOFTOP",
            "viewport" : {
               "northeast" : {
                  "lat" : 25.0685403802915,
                  "lng" : 121.5165519802915
               },
               "southwest" : {
                  "lat" : 25.0658424197085,
                  "lng" : 121.5138540197085
               }
            }
         },
         "place_id" : "ChIJfVHdnUepQjQRjwa-AWWpZqY",
         "types" : [ "street_address" ]
      }
   ],
   "status" : "OK"
}

