{
   "results" : [
      {
         "address_components" : [
            {
               "long_name" : "296",
               "short_name" : "296",
               "types" : [ "street_number" ]
            },
            {
               "long_name" : "Tayou Road",
               "short_name" : "Tayou Rd",
               "types" : [ "route" ]
            },
            {
               "long_name" : "·s¯q¨½",
               "short_name" : "·s¯q¨½",
               "types" : [ "administrative_area_level_4", "political" ]
            },
            {
               "long_name" : "Songshan District",
               "short_name" : "Songshan District",
               "types" : [ "administrative_area_level_3", "political" ]
            },
            {
               "long_name" : "Taipei City",
               "short_name" : "Taipei City",
               "types" : [ "administrative_area_level_1", "political" ]
            },
            {
               "long_name" : "Taiwan",
               "short_name" : "TW",
               "types" : [ "country", "political" ]
            },
            {
               "long_name" : "105",
               "short_name" : "105",
               "types" : [ "postal_code" ]
            }
         ],
         "formatted_address" : "No. 296, Tayou Rd, Songshan District, Taipei City, Taiwan 105",
         "geometry" : {
            "location" : {
               "lat" : 25.0599927,
               "lng" : 121.5686425
            },
            "location_type" : "ROOFTOP",
            "viewport" : {
               "northeast" : {
                  "lat" : 25.0613416802915,
                  "lng" : 121.5699914802915
               },
               "southwest" : {
                  "lat" : 25.0586437197085,
                  "lng" : 121.5672935197085
               }
            }
         },
         "place_id" : "ChIJO_fhAI-rQjQRaM-RrTbjwiQ",
         "types" : [ "street_address" ]
      }
   ],
   "status" : "OK"
}

