{
   "results" : [
      {
         "address_components" : [
            {
               "long_name" : "7",
               "short_name" : "7",
               "types" : [ "street_number" ]
            },
            {
               "long_name" : "Section 4, Zhongxiao East Road",
               "short_name" : "Section 4, Zhongxiao E Rd",
               "types" : [ "route" ]
            },
            {
               "long_name" : "¥úªZ¨½",
               "short_name" : "¥úªZ¨½",
               "types" : [ "administrative_area_level_4", "political" ]
            },
            {
               "long_name" : "Da¡¦an District",
               "short_name" : "Da¡¦an District",
               "types" : [ "administrative_area_level_3", "political" ]
            },
            {
               "long_name" : "Taipei City",
               "short_name" : "Taipei City",
               "types" : [ "administrative_area_level_1", "political" ]
            },
            {
               "long_name" : "Taiwan",
               "short_name" : "TW",
               "types" : [ "country", "political" ]
            },
            {
               "long_name" : "106",
               "short_name" : "106",
               "types" : [ "postal_code" ]
            }
         ],
         "formatted_address" : "No. 7, Section 4, Zhongxiao E Rd, Da¡¦an District, Taipei City, Taiwan 106",
         "geometry" : {
            "location" : {
               "lat" : 25.041883,
               "lng" : 121.544274
            },
            "location_type" : "ROOFTOP",
            "viewport" : {
               "northeast" : {
                  "lat" : 25.0432319802915,
                  "lng" : 121.5456229802915
               },
               "southwest" : {
                  "lat" : 25.0405340197085,
                  "lng" : 121.5429250197085
               }
            }
         },
         "place_id" : "ChIJ98T8dNqrQjQRV5C4EzFc9XY",
         "types" : [ "street_address" ]
      }
   ],
   "status" : "OK"
}

