{
   "results" : [
      {
         "address_components" : [
            {
               "long_name" : "11",
               "short_name" : "11",
               "types" : [ "street_number" ]
            },
            {
               "long_name" : "Alley 11, Lane 266, Shidong Road",
               "short_name" : "Alley 11, Lane 266, Shidong Rd",
               "types" : [ "route" ]
            },
            {
               "long_name" : "ªÛ¤s¨½",
               "short_name" : "ªÛ¤s¨½",
               "types" : [ "administrative_area_level_4", "political" ]
            },
            {
               "long_name" : "Shilin District",
               "short_name" : "Shilin District",
               "types" : [ "administrative_area_level_3", "political" ]
            },
            {
               "long_name" : "Taipei City",
               "short_name" : "Taipei City",
               "types" : [ "administrative_area_level_1", "political" ]
            },
            {
               "long_name" : "Taiwan",
               "short_name" : "TW",
               "types" : [ "country", "political" ]
            },
            {
               "long_name" : "111",
               "short_name" : "111",
               "types" : [ "postal_code" ]
            }
         ],
         "formatted_address" : "No. 11, Alley 11, Lane 266, Shidong Rd, Shilin District, Taipei City, Taiwan 111",
         "geometry" : {
            "location" : {
               "lat" : 25.1119971,
               "lng" : 121.5372971
            },
            "location_type" : "ROOFTOP",
            "viewport" : {
               "northeast" : {
                  "lat" : 25.1133460802915,
                  "lng" : 121.5386460802915
               },
               "southwest" : {
                  "lat" : 25.1106481197085,
                  "lng" : 121.5359481197085
               }
            }
         },
         "place_id" : "ChIJ03mk_imsQjQR04TL4NT2a3Q",
         "types" : [ "street_address" ]
      }
   ],
   "status" : "OK"
}

