{
   "results" : [
      {
         "address_components" : [
            {
               "long_name" : "234",
               "short_name" : "234",
               "types" : [ "street_number" ]
            },
            {
               "long_name" : "Section 4, Bade Road",
               "short_name" : "Section 4, Bade Rd",
               "types" : [ "route" ]
            },
            {
               "long_name" : "´_²±¨½",
               "short_name" : "´_²±¨½",
               "types" : [ "administrative_area_level_4", "political" ]
            },
            {
               "long_name" : "Songshan District",
               "short_name" : "Songshan District",
               "types" : [ "administrative_area_level_3", "political" ]
            },
            {
               "long_name" : "Taipei City",
               "short_name" : "Taipei City",
               "types" : [ "administrative_area_level_1", "political" ]
            },
            {
               "long_name" : "Taiwan",
               "short_name" : "TW",
               "types" : [ "country", "political" ]
            },
            {
               "long_name" : "105",
               "short_name" : "105",
               "types" : [ "postal_code" ]
            }
         ],
         "formatted_address" : "No. 234, Section 4, Bade Rd, Songshan District, Taipei City, Taiwan 105",
         "geometry" : {
            "location" : {
               "lat" : 25.0488197,
               "lng" : 121.5651696
            },
            "location_type" : "ROOFTOP",
            "viewport" : {
               "northeast" : {
                  "lat" : 25.0501686802915,
                  "lng" : 121.5665185802915
               },
               "southwest" : {
                  "lat" : 25.0474707197085,
                  "lng" : 121.5638206197085
               }
            }
         },
         "place_id" : "ChIJ4wno3ZWrQjQRTX40Avp0HeE",
         "types" : [ "street_address" ]
      }
   ],
   "status" : "OK"
}

