{
   "results" : [
      {
         "address_components" : [
            {
               "long_name" : "100",
               "short_name" : "100",
               "types" : [ "street_number" ]
            },
            {
               "long_name" : "Section 3, Roosevelt Road",
               "short_name" : "Section 3, Roosevelt Rd",
               "types" : [ "route" ]
            },
            {
               "long_name" : "³»ªF¨½",
               "short_name" : "³»ªF¨½",
               "types" : [ "administrative_area_level_4", "political" ]
            },
            {
               "long_name" : "Zhongzheng District",
               "short_name" : "Zhongzheng District",
               "types" : [ "administrative_area_level_3", "political" ]
            },
            {
               "long_name" : "Taipei City",
               "short_name" : "Taipei City",
               "types" : [ "administrative_area_level_1", "political" ]
            },
            {
               "long_name" : "Taiwan",
               "short_name" : "TW",
               "types" : [ "country", "political" ]
            },
            {
               "long_name" : "100",
               "short_name" : "100",
               "types" : [ "postal_code" ]
            }
         ],
         "formatted_address" : "No. 100, Section 3, Roosevelt Rd, Zhongzheng District, Taipei City, Taiwan 100",
         "geometry" : {
            "bounds" : {
               "northeast" : {
                  "lat" : 25.0213876,
                  "lng" : 121.5272859
               },
               "southwest" : {
                  "lat" : 25.0213754,
                  "lng" : 121.5272729
               }
            },
            "location" : {
               "lat" : 25.0213754,
               "lng" : 121.5272729
            },
            "location_type" : "RANGE_INTERPOLATED",
            "viewport" : {
               "northeast" : {
                  "lat" : 25.0227304802915,
                  "lng" : 121.5286283802915
               },
               "southwest" : {
                  "lat" : 25.0200325197085,
                  "lng" : 121.5259304197085
               }
            }
         },
         "place_id" : "EjMxMDDlj7DngaPlj7DljJfluILkuK3mraPljYDnvoXmlq_npo_ot6_kuInmrrUxMDDomZ8",
         "types" : [ "street_address" ]
      }
   ],
   "status" : "OK"
}

