{
   "results" : [
      {
         "address_components" : [
            {
               "long_name" : "204",
               "short_name" : "204",
               "types" : [ "street_number" ]
            },
            {
               "long_name" : "Kangle Street",
               "short_name" : "Kangle St",
               "types" : [ "route" ]
            },
            {
               "long_name" : "¤º·¾¨½",
               "short_name" : "¤º·¾¨½",
               "types" : [ "administrative_area_level_4", "political" ]
            },
            {
               "long_name" : "Neihu District",
               "short_name" : "Neihu District",
               "types" : [ "administrative_area_level_3", "political" ]
            },
            {
               "long_name" : "Taipei City",
               "short_name" : "Taipei City",
               "types" : [ "administrative_area_level_1", "political" ]
            },
            {
               "long_name" : "Taiwan",
               "short_name" : "TW",
               "types" : [ "country", "political" ]
            },
            {
               "long_name" : "114",
               "short_name" : "114",
               "types" : [ "postal_code" ]
            }
         ],
         "formatted_address" : "No. 204, Kangle St, Neihu District, Taipei City, Taiwan 114",
         "geometry" : {
            "location" : {
               "lat" : 25.0763143,
               "lng" : 121.6213159
            },
            "location_type" : "ROOFTOP",
            "viewport" : {
               "northeast" : {
                  "lat" : 25.0776632802915,
                  "lng" : 121.6226648802915
               },
               "southwest" : {
                  "lat" : 25.0749653197085,
                  "lng" : 121.6199669197085
               }
            }
         },
         "partial_match" : true,
         "place_id" : "ChIJyQg_H7asQjQRWt7dDmvFXm0",
         "types" : [ "street_address" ]
      }
   ],
   "status" : "OK"
}

