{
   "results" : [
      {
         "address_components" : [
            {
               "long_name" : "72",
               "short_name" : "72",
               "types" : [ "street_number" ]
            },
            {
               "long_name" : "Dongming Street",
               "short_name" : "Dongming St",
               "types" : [ "route" ]
            },
            {
               "long_name" : "東明里",
               "short_name" : "東明里",
               "types" : [ "administrative_area_level_4", "political" ]
            },
            {
               "long_name" : "Nangang District",
               "short_name" : "Nangang District",
               "types" : [ "administrative_area_level_3", "political" ]
            },
            {
               "long_name" : "Taipei City",
               "short_name" : "Taipei City",
               "types" : [ "administrative_area_level_1", "political" ]
            },
            {
               "long_name" : "Taiwan",
               "short_name" : "TW",
               "types" : [ "country", "political" ]
            },
            {
               "long_name" : "115",
               "short_name" : "115",
               "types" : [ "postal_code" ]
            }
         ],
         "formatted_address" : "No. 72, Dongming St, Nangang District, Taipei City, Taiwan 115",
         "geometry" : {
            "location" : {
               "lat" : 25.0548201,
               "lng" : 121.6025741
            },
            "location_type" : "ROOFTOP",
            "viewport" : {
               "northeast" : {
                  "lat" : 25.0561690802915,
                  "lng" : 121.6039230802915
               },
               "southwest" : {
                  "lat" : 25.0534711197085,
                  "lng" : 121.6012251197085
               }
            }
         },
         "place_id" : "ChIJj1shKmGrQjQRdcXbQ9vL4Tc",
         "types" : [ "street_address" ]
      }
   ],
   "status" : "OK"
}

