{
   "results" : [
      {
         "address_components" : [
            {
               "long_name" : "2",
               "short_name" : "2",
               "types" : [ "street_number" ]
            },
            {
               "long_name" : "Lane 121, Hulin Street",
               "short_name" : "Lane 121, Hulin St",
               "types" : [ "route" ]
            },
            {
               "long_name" : "¼s©~¨½",
               "short_name" : "¼s©~¨½",
               "types" : [ "administrative_area_level_4", "political" ]
            },
            {
               "long_name" : "Xinyi District",
               "short_name" : "Xinyi District",
               "types" : [ "administrative_area_level_3", "political" ]
            },
            {
               "long_name" : "Taipei City",
               "short_name" : "Taipei City",
               "types" : [ "administrative_area_level_1", "political" ]
            },
            {
               "long_name" : "Taiwan",
               "short_name" : "TW",
               "types" : [ "country", "political" ]
            },
            {
               "long_name" : "110",
               "short_name" : "110",
               "types" : [ "postal_code" ]
            }
         ],
         "formatted_address" : "No. 2, Lane 121, Hulin St, Xinyi District, Taipei City, Taiwan 110",
         "geometry" : {
            "location" : {
               "lat" : 25.0402219,
               "lng" : 121.576974
            },
            "location_type" : "ROOFTOP",
            "viewport" : {
               "northeast" : {
                  "lat" : 25.0415708802915,
                  "lng" : 121.5783229802915
               },
               "southwest" : {
                  "lat" : 25.0388729197085,
                  "lng" : 121.5756250197085
               }
            }
         },
         "place_id" : "ChIJYZWhWKGrQjQRg6TU-2wOMMY",
         "types" : [ "street_address" ]
      }
   ],
   "status" : "OK"
}

