{
   "results" : [
      {
         "address_components" : [
            {
               "long_name" : "217",
               "short_name" : "217",
               "types" : [ "street_number" ]
            },
            {
               "long_name" : "Section 3, Nanjing East Road",
               "short_name" : "Section 3, Nanjing E Rd",
               "types" : [ "route" ]
            },
            {
               "long_name" : "´_µØ¨½",
               "short_name" : "´_µØ¨½",
               "types" : [ "administrative_area_level_4", "political" ]
            },
            {
               "long_name" : "Zhongshan District",
               "short_name" : "Zhongshan District",
               "types" : [ "administrative_area_level_3", "political" ]
            },
            {
               "long_name" : "Taipei City",
               "short_name" : "Taipei City",
               "types" : [ "administrative_area_level_1", "political" ]
            },
            {
               "long_name" : "Taiwan",
               "short_name" : "TW",
               "types" : [ "country", "political" ]
            },
            {
               "long_name" : "104",
               "short_name" : "104",
               "types" : [ "postal_code" ]
            }
         ],
         "formatted_address" : "No. 217, Section 3, Nanjing E Rd, Zhongshan District, Taipei City, Taiwan 104",
         "geometry" : {
            "location" : {
               "lat" : 25.052129,
               "lng" : 121.542913
            },
            "location_type" : "ROOFTOP",
            "viewport" : {
               "northeast" : {
                  "lat" : 25.0534779802915,
                  "lng" : 121.5442619802915
               },
               "southwest" : {
                  "lat" : 25.05078001970849,
                  "lng" : 121.5415640197085
               }
            }
         },
         "place_id" : "ChIJ5cX4_N2rQjQR0GP1LSx_Eoo",
         "types" : [ "street_address" ]
      }
   ],
   "status" : "OK"
}

