{
   "results" : [
      {
         "address_components" : [
            {
               "long_name" : "209",
               "short_name" : "209",
               "types" : [ "street_number" ]
            },
            {
               "long_name" : "Section 1, Civic Boulevard",
               "short_name" : "Section 1, Civic Blvd",
               "types" : [ "route" ]
            },
            {
               "long_name" : "建明里",
               "short_name" : "建明里",
               "types" : [ "administrative_area_level_4", "political" ]
            },
            {
               "long_name" : "Datong District",
               "short_name" : "Datong District",
               "types" : [ "administrative_area_level_3", "political" ]
            },
            {
               "long_name" : "Taipei City",
               "short_name" : "Taipei City",
               "types" : [ "administrative_area_level_1", "political" ]
            },
            {
               "long_name" : "Taiwan",
               "short_name" : "TW",
               "types" : [ "country", "political" ]
            },
            {
               "long_name" : "103",
               "short_name" : "103",
               "types" : [ "postal_code" ]
            }
         ],
         "formatted_address" : "No. 209, Section 1, Civic Blvd, Datong District, Taipei City, Taiwan 103",
         "geometry" : {
            "location" : {
               "lat" : 25.0487857,
               "lng" : 121.518569
            },
            "location_type" : "ROOFTOP",
            "viewport" : {
               "northeast" : {
                  "lat" : 25.0501346802915,
                  "lng" : 121.5199179802915
               },
               "southwest" : {
                  "lat" : 25.0474367197085,
                  "lng" : 121.5172200197085
               }
            }
         },
         "place_id" : "ChIJZ3Bl622pQjQR0qw_1goAzaI",
         "types" : [ "street_address" ]
      }
   ],
   "status" : "OK"
}

