{
   "results" : [
      {
         "address_components" : [
            {
               "long_name" : "70",
               "short_name" : "70",
               "types" : [ "street_number" ]
            },
            {
               "long_name" : "Section 5, Nanjing East Road",
               "short_name" : "Section 5, Nanjing E Rd",
               "types" : [ "route" ]
            },
            {
               "long_name" : "¦N²»¨½",
               "short_name" : "¦N²»¨½",
               "types" : [ "administrative_area_level_4", "political" ]
            },
            {
               "long_name" : "Songshan District",
               "short_name" : "Songshan District",
               "types" : [ "administrative_area_level_3", "political" ]
            },
            {
               "long_name" : "Taipei City",
               "short_name" : "Taipei City",
               "types" : [ "administrative_area_level_1", "political" ]
            },
            {
               "long_name" : "Taiwan",
               "short_name" : "TW",
               "types" : [ "country", "political" ]
            },
            {
               "long_name" : "105",
               "short_name" : "105",
               "types" : [ "postal_code" ]
            }
         ],
         "formatted_address" : "No. 70, Section 5, Nanjing E Rd, Songshan District, Taipei City, Taiwan 105",
         "geometry" : {
            "location" : {
               "lat" : 25.0512618,
               "lng" : 121.5609755
            },
            "location_type" : "ROOFTOP",
            "viewport" : {
               "northeast" : {
                  "lat" : 25.0526107802915,
                  "lng" : 121.5623244802915
               },
               "southwest" : {
                  "lat" : 25.0499128197085,
                  "lng" : 121.5596265197085
               }
            }
         },
         "place_id" : "ChIJD9vO3pSrQjQR75FocqymKwo",
         "types" : [ "street_address" ]
      }
   ],
   "status" : "OK"
}

