{
   "results" : [
      {
         "address_components" : [
            {
               "long_name" : "520",
               "short_name" : "520",
               "types" : [ "street_number" ]
            },
            {
               "long_name" : "Section 4, Bade Road",
               "short_name" : "Section 4, Bade Rd",
               "types" : [ "route" ]
            },
            {
               "long_name" : "Songshan District",
               "short_name" : "Songshan District",
               "types" : [ "administrative_area_level_3", "political" ]
            },
            {
               "long_name" : "Taipei City",
               "short_name" : "Taipei City",
               "types" : [ "administrative_area_level_1", "political" ]
            },
            {
               "long_name" : "Taiwan",
               "short_name" : "TW",
               "types" : [ "country", "political" ]
            },
            {
               "long_name" : "105",
               "short_name" : "105",
               "types" : [ "postal_code" ]
            }
         ],
         "formatted_address" : "No. 520, Section 4, Bade Rd, Songshan District, Taipei City, Taiwan 105",
         "geometry" : {
            "location" : {
               "lat" : 25.04976,
               "lng" : 121.5711099
            },
            "location_type" : "ROOFTOP",
            "viewport" : {
               "northeast" : {
                  "lat" : 25.0511089802915,
                  "lng" : 121.5724588802915
               },
               "southwest" : {
                  "lat" : 25.0484110197085,
                  "lng" : 121.5697609197085
               }
            }
         },
         "place_id" : "ChIJrWGlYZerQjQRvOo8CBc4_DI",
         "types" : [ "street_address" ]
      }
   ],
   "status" : "OK"
}

