{
   "results" : [
      {
         "address_components" : [
            {
               "long_name" : "23",
               "short_name" : "23",
               "types" : [ "street_number" ]
            },
            {
               "long_name" : "Alley 3, Lane 66, Section 5, Nanjing East Road",
               "short_name" : "Alley 3, Lane 66, Section 5, Nanjing E Rd",
               "types" : [ "route" ]
            },
            {
               "long_name" : "¦N²»¨½",
               "short_name" : "¦N²»¨½",
               "types" : [ "administrative_area_level_4", "political" ]
            },
            {
               "long_name" : "Songshan District",
               "short_name" : "Songshan District",
               "types" : [ "administrative_area_level_3", "political" ]
            },
            {
               "long_name" : "Taipei City",
               "short_name" : "Taipei City",
               "types" : [ "administrative_area_level_1", "political" ]
            },
            {
               "long_name" : "Taiwan",
               "short_name" : "TW",
               "types" : [ "country", "political" ]
            },
            {
               "long_name" : "105",
               "short_name" : "105",
               "types" : [ "postal_code" ]
            }
         ],
         "formatted_address" : "No. 23, Alley 3, Lane 66, Section 5, Nanjing E Rd, Songshan District, Taipei City, Taiwan 105",
         "geometry" : {
            "location" : {
               "lat" : 25.0510171,
               "lng" : 121.5616142
            },
            "location_type" : "ROOFTOP",
            "viewport" : {
               "northeast" : {
                  "lat" : 25.0523660802915,
                  "lng" : 121.5629631802915
               },
               "southwest" : {
                  "lat" : 25.0496681197085,
                  "lng" : 121.5602652197085
               }
            }
         },
         "place_id" : "ChIJI9br4ZSrQjQRLQ0_enpNPkY",
         "types" : [ "street_address" ]
      }
   ],
   "status" : "OK"
}

