{
   "results" : [
      {
         "address_components" : [
            {
               "long_name" : "170",
               "short_name" : "170",
               "types" : [ "street_number" ]
            },
            {
               "long_name" : "Section 2, Zhongshan North Road",
               "short_name" : "Section 2, Zhongshan N Rd",
               "types" : [ "route" ]
            },
            {
               "long_name" : "集英里",
               "short_name" : "集英里",
               "types" : [ "administrative_area_level_4", "political" ]
            },
            {
               "long_name" : "Zhongshan District",
               "short_name" : "Zhongshan District",
               "types" : [ "administrative_area_level_3", "political" ]
            },
            {
               "long_name" : "Taipei City",
               "short_name" : "Taipei City",
               "types" : [ "administrative_area_level_1", "political" ]
            },
            {
               "long_name" : "Taiwan",
               "short_name" : "TW",
               "types" : [ "country", "political" ]
            },
            {
               "long_name" : "104",
               "short_name" : "104",
               "types" : [ "postal_code" ]
            }
         ],
         "formatted_address" : "No. 170, Section 2, Zhongshan N Rd, Zhongshan District, Taipei City, Taiwan 104",
         "geometry" : {
            "bounds" : {
               "northeast" : {
                  "lat" : 25.0633197,
                  "lng" : 121.5223989
               },
               "southwest" : {
                  "lat" : 25.0633165,
                  "lng" : 121.5223805
               }
            },
            "location" : {
               "lat" : 25.0633165,
               "lng" : 121.5223805
            },
            "location_type" : "RANGE_INTERPOLATED",
            "viewport" : {
               "northeast" : {
                  "lat" : 25.0646670802915,
                  "lng" : 121.5237386802915
               },
               "southwest" : {
                  "lat" : 25.0619691197085,
                  "lng" : 121.5210407197085
               }
            }
         },
         "place_id" : "EjMxMDTlj7DngaPlj7DljJfluILkuK3lsbHljYDkuK3lsbHljJfot6_kuozmrrUxNzDomZ8",
         "types" : [ "street_address" ]
      }
   ],
   "status" : "OK"
}

