{
   "results" : [
      {
         "address_components" : [
            {
               "long_name" : "46",
               "short_name" : "46",
               "types" : [ "street_number" ]
            },
            {
               "long_name" : "Lane 154, Dechang Street",
               "short_name" : "Lane 154, Dechang St",
               "types" : [ "route" ]
            },
            {
               "long_name" : "©¾¼w¨½",
               "short_name" : "©¾¼w¨½",
               "types" : [ "administrative_area_level_4", "political" ]
            },
            {
               "long_name" : "Wanhua District",
               "short_name" : "Wanhua District",
               "types" : [ "administrative_area_level_3", "political" ]
            },
            {
               "long_name" : "Taipei City",
               "short_name" : "Taipei City",
               "types" : [ "administrative_area_level_1", "political" ]
            },
            {
               "long_name" : "Taiwan",
               "short_name" : "TW",
               "types" : [ "country", "political" ]
            },
            {
               "long_name" : "108",
               "short_name" : "108",
               "types" : [ "postal_code" ]
            }
         ],
         "formatted_address" : "No. 46, Lane 154, Dechang St, Wanhua District, Taipei City, Taiwan 108",
         "geometry" : {
            "location" : {
               "lat" : 25.0244918,
               "lng" : 121.4959018
            },
            "location_type" : "ROOFTOP",
            "viewport" : {
               "northeast" : {
                  "lat" : 25.0258407802915,
                  "lng" : 121.4972507802915
               },
               "southwest" : {
                  "lat" : 25.0231428197085,
                  "lng" : 121.4945528197085
               }
            }
         },
         "place_id" : "ChIJvaZHN7SpQjQRMDScaV53ZdY",
         "types" : [ "street_address" ]
      }
   ],
   "status" : "OK"
}

