{
   "results" : [
      {
         "address_components" : [
            {
               "long_name" : "1-17",
               "short_name" : "1-17",
               "types" : [ "street_number" ]
            },
            {
               "long_name" : "Bao'an Street",
               "short_name" : "Bao'an St",
               "types" : [ "route" ]
            },
            {
               "long_name" : "民權里",
               "short_name" : "民權里",
               "types" : [ "administrative_area_level_4", "political" ]
            },
            {
               "long_name" : "Datong District",
               "short_name" : "Datong District",
               "types" : [ "administrative_area_level_3", "political" ]
            },
            {
               "long_name" : "Taipei City",
               "short_name" : "Taipei City",
               "types" : [ "administrative_area_level_1", "political" ]
            },
            {
               "long_name" : "Taiwan",
               "short_name" : "TW",
               "types" : [ "country", "political" ]
            },
            {
               "long_name" : "103",
               "short_name" : "103",
               "types" : [ "postal_code" ]
            }
         ],
         "formatted_address" : "No. 1-17, Bao'an St, Datong District, Taipei City, Taiwan 103",
         "geometry" : {
            "location" : {
               "lat" : 25.0597449,
               "lng" : 121.514301
            },
            "location_type" : "ROOFTOP",
            "viewport" : {
               "northeast" : {
                  "lat" : 25.0610938802915,
                  "lng" : 121.5156499802915
               },
               "southwest" : {
                  "lat" : 25.0583959197085,
                  "lng" : 121.5129520197085
               }
            }
         },
         "place_id" : "ChIJnWolB0CpQjQRAQ0x9WStS18",
         "types" : [ "street_address" ]
      }
   ],
   "status" : "OK"
}

