{
   "results" : [
      {
         "address_components" : [
            {
               "long_name" : "280",
               "short_name" : "280",
               "types" : [ "street_number" ]
            },
            {
               "long_name" : "Minsheng West Road",
               "short_name" : "Minsheng W Rd",
               "types" : [ "route" ]
            },
            {
               "long_name" : "는때㉬",
               "short_name" : "는때㉬",
               "types" : [ "administrative_area_level_4", "political" ]
            },
            {
               "long_name" : "Datong District",
               "short_name" : "Datong District",
               "types" : [ "administrative_area_level_3", "political" ]
            },
            {
               "long_name" : "Taipei City",
               "short_name" : "Taipei City",
               "types" : [ "administrative_area_level_1", "political" ]
            },
            {
               "long_name" : "Taiwan",
               "short_name" : "TW",
               "types" : [ "country", "political" ]
            },
            {
               "long_name" : "103",
               "short_name" : "103",
               "types" : [ "postal_code" ]
            }
         ],
         "formatted_address" : "No. 280, Minsheng W Rd, Datong District, Taipei City, Taiwan 103",
         "geometry" : {
            "location" : {
               "lat" : 25.0568723,
               "lng" : 121.5130219
            },
            "location_type" : "ROOFTOP",
            "viewport" : {
               "northeast" : {
                  "lat" : 25.0582212802915,
                  "lng" : 121.5143708802915
               },
               "southwest" : {
                  "lat" : 25.0555233197085,
                  "lng" : 121.5116729197085
               }
            }
         },
         "place_id" : "ChIJq9wj3xSpQjQRFZndBk9SQOU",
         "types" : [ "street_address" ]
      }
   ],
   "status" : "OK"
}

